slacknotif.py
slacknotifpy-1.0.7.dist-info/LICENSE
slacknotifpy-1.0.7.dist-info/METADATA
slacknotifpy-1.0.7.dist-info/WHEEL
slacknotifpy-1.0.7.dist-info/entry_points.txt
slacknotifpy-1.0.7.dist-info/top_level.txt
slacknotifpy-1.0.7.dist-info/RECORD
