Metadata-Version: 2.1
Name: slacknotifpy
Version: 1.0.7
Summary: A Python tool for sending Slack notifications on job completion.
Home-page: https://github.com/zeinhajjali/slacknotifpy
Author: Zein Hajj-Ali
Author-email: zeinhajjali@outlook.com
Classifier: Programming Language :: Python :: 3
Classifier: License :: OSI Approved :: MIT License
Classifier: Operating System :: OS Independent
Requires-Python: >=3.6
License-File: LICENSE
Requires-Dist: slack_bolt
